{
  "objectInfo" : {
    "id" : "64oJrJu1G4KhVncCWzxt8q",
    "name" : "Mapping1 - Copy 1 - Copy 1 - Copy 1",
    "type" : "DTEMPLATE",
    "metadata" : {
      "modelVersion" : {
        "major" : 0,
        "minor" : 0
      },
      "repoInfo" : {
        "repoHandle" : "0112NC170000000007J5"
      },
      "contextAttributes" : [ {
        "name" : "id",
        "value" : "@1"
      } ],
      "additionalInfo" : {
        "description" : "",
        "contentType" : null,
        "documentState" : "INVALID"
      }
    }
  },
  "dataFileExtension" : "zip",
  "objectRefs" : [ ]
}