{
  "objectInfo" : {
    "id" : "4FT81ge2KdCkLl33toioyV",
    "name" : "LTF_inlineActionDepen2",
    "type" : "WORKFLOW",
    "metadata" : {
      "modelVersion" : {
        "major" : 0,
        "minor" : 0
      },
      "repoInfo" : {
        "repoHandle" : "010PGG0N000000000003"
      },
      "contextAttributes" : [ {
        "name" : "id",
        "value" : "@1"
      } ],
      "additionalInfo" : {
        "description" : null,
        "contentType" : "JSON",
        "documentState" : "VALID"
      }
    }
  },
  "dataFileExtension" : "zip",
  "objectRefs" : [ {
    "id" : "3509jRVCrRgfCxbB0kdoM3",
    "name" : "MCT_inlineActionDepen2",
    "type" : "MTT",
    "metadata" : {
      "modelVersion" : {
        "major" : 0,
        "minor" : 0
      },
      "repoInfo" : {
        "repoHandle" : "010PGG0Z000000000003"
      },
      "contextAttributes" : [ {
        "name" : "id",
        "value" : "@1"
      } ],
      "additionalInfo" : {
        "description" : "",
        "contentType" : "JSON",
        "documentState" : "VALID"
      }
    },
    "path" : "/Explore/InlineActionsProjectDepen"
  }, {
    "id" : "dvBSyxuKowDcGFZzVjF245",
    "name" : "drs_inlineActionDepen",
    "type" : "DRS",
    "metadata" : {
      "modelVersion" : {
        "major" : 0,
        "minor" : 0
      },
      "repoInfo" : {
        "repoHandle" : "010PGG0G000000000002"
      },
      "contextAttributes" : null,
      "additionalInfo" : {
        "description" : null,
        "contentType" : "JSON",
        "documentState" : "VALID"
      }
    },
    "path" : "/Explore/InlineActionsProjectDepen"
  }, {
    "id" : "hSsgiyyOOOabhfYCTDiwmo",
    "name" : "PCS_inlineActionDepen",
    "type" : "PCS",
    "metadata" : {
      "modelVersion" : {
        "major" : 0,
        "minor" : 0
      },
      "repoInfo" : {
        "repoHandle" : "010PGG0K000000000002"
      },
      "contextAttributes" : null,
      "additionalInfo" : {
        "description" : null,
        "contentType" : "JSON",
        "documentState" : "VALID"
      }
    },
    "path" : "/Explore/InlineActionsProjectDepen"
  }, {
    "id" : "aQEuFH8QfaJdwMNCnevyEU",
    "name" : "dss_inlineActionDepen",
    "type" : "DSS",
    "metadata" : {
      "modelVersion" : {
        "major" : 0,
        "minor" : 0
      },
      "repoInfo" : {
        "repoHandle" : "010PGG0I000000000002"
      },
      "contextAttributes" : null,
      "additionalInfo" : {
        "description" : "",
        "contentType" : "JSON",
        "documentState" : "VALID"
      }
    },
    "path" : "/Explore/InlineActionsProjectDepen"
  } ]
}